qd2_controller/__init__.py
qd2_controller/bb84_att.py
qd2_controller/bb84_with_eve.py
qd2_controller/controller.py
qd2_controller/Non_ideal_QKDN/CITATION.cff
qd2_controller/Non_ideal_QKDN/LICENSE
qd2_controller/Non_ideal_QKDN/README.md
qd2_controller/Non_ideal_QKDN/__init__.py
qd2_controller/Non_ideal_QKDN/math_tools.py
qd2_controller/Non_ideal_QKDN/network.py
qd2_controller/Non_ideal_QKDN/requirements.txt
qd2_controller/Non_ideal_QKDN/bb84/__init__.py
qd2_controller/Non_ideal_QKDN/bb84/basic_protocol.py
qd2_controller/Non_ideal_QKDN/bb84/bb84_protocol.py
qd2_controller/Non_ideal_QKDN/bb84/key_exchange.py
qd2_controller/Non_ideal_QKDN/bb84/params.yaml
qd2_controller/Non_ideal_QKDN/bb84/receiver_protocol.py
qd2_controller/Non_ideal_QKDN/bb84/sender_protocol.py
qd2_controller/Non_ideal_QKDN/cascade_python/.gitignore
qd2_controller/Non_ideal_QKDN/cascade_python/.readthedocs.yaml
qd2_controller/Non_ideal_QKDN/cascade_python/.travis.yml
qd2_controller/Non_ideal_QKDN/cascade_python/LICENSE
qd2_controller/Non_ideal_QKDN/cascade_python/Makefile
qd2_controller/Non_ideal_QKDN/cascade_python/README.rst
qd2_controller/Non_ideal_QKDN/cascade_python/doc8.ini
qd2_controller/Non_ideal_QKDN/cascade_python/profile.png
qd2_controller/Non_ideal_QKDN/cascade_python/pylintrc
qd2_controller/Non_ideal_QKDN/cascade_python/requirements.txt
qd2_controller/Non_ideal_QKDN/cascade_python/.vscode/launch.json
qd2_controller/Non_ideal_QKDN/cascade_python/.vscode/settings.json
qd2_controller/Non_ideal_QKDN/cascade_python/.vscode/spellright.dict
qd2_controller/Non_ideal_QKDN/cascade_python/cascade/__init__.py
qd2_controller/Non_ideal_QKDN/cascade_python/cascade/algorithm.py
qd2_controller/Non_ideal_QKDN/cascade_python/cascade/block.py
qd2_controller/Non_ideal_QKDN/cascade_python/cascade/classical_channel.py
qd2_controller/Non_ideal_QKDN/cascade_python/cascade/key.py
qd2_controller/Non_ideal_QKDN/cascade_python/cascade/mock_classical_channel.py
qd2_controller-1.1.3.dist-info/METADATA
qd2_controller-1.1.3.dist-info/WHEEL
qd2_controller-1.1.3.dist-info/RECORD
