Metadata-Version: 2.4
Name: qd2_controller
Version: 1.1.3
Summary: Software for Quditto controller
Author-email: Javier Perez <javier.perez@imdea.org>, Blanca Lopez <blanca.lopez@imdea.org>, Angela Diaz <angela.diaz@imdea.org>
Requires-Python: >=3.8
Requires-Dist: aio-pika~=9.5.5
Requires-Dist: cryptomite
Requires-Dist: fastapi~=0.115.11
Requires-Dist: netsquid
Requires-Dist: numpy==1.24.4
Requires-Dist: pika~=1.3.2
Requires-Dist: pydynaa==1.0.2
Requires-Dist: scipy==1.9.3
Requires-Dist: uvicorn~=0.34.0
